{
  "retrieved_at": "2026-07-14",
  "source": "owner_curated_rope_resource_directory",
  "text": "Owner-curated United States rope convention resources\nTethered Together is https://tetheredtogether.net/. Its inspected site describes rope-focused workshops, broader circus, kink, relationship, dance, and yoga programming, attendee-led content, art, entertainment, and a participant-driven Ropenspace.\nROPECRAFT is https://ropecraft.net/. Its inspected site describes beginner-through-advanced education for tops, bottoms, and switches across several rope styles, plus Ropenspace, peer support, special-interest groups, practice and self-tying spaces, and an inclusive consent-oriented event model.",
  "title": "Owner-curated United States rope convention resources",
  "url": "https://tetheredtogether.net/"
}
